oradad_file/__init__.py
oradad_file/config.py
oradad_file/oradad_file.py
oradad_file-0.1.0.dist-info/WHEEL
oradad_file-0.1.0.dist-info/METADATA
oradad_file-0.1.0.dist-info/RECORD
