Metadata-Version: 2.1
Name: oradad-file
Version: 0.1.0
Summary: Oradad File reader in python3
License: MIT
Author: Léonard Moreau
Author-email: leonard@moreau.cloud
Requires-Python: >=3.7,<4.0
Classifier: License :: OSI Approved :: MIT License
Classifier: Programming Language :: Python :: 3
Classifier: Programming Language :: Python :: 3.7
Classifier: Programming Language :: Python :: 3.8
Classifier: Programming Language :: Python :: 3.9
Requires-Dist: lz4 (>=3.1.1,<4.0.0)
Requires-Dist: pathlib (>=1.0.1,<2.0.0)
Requires-Dist: pycrypto (>=2.6.1,<3.0.0)
Requires-Dist: rsa (>=4.6,<5.0)
